iex/__init__.py
iex/simple.py
jasanpy/__init__.py
jasanpy/lookup/__init__.py
jasanpy/lookup/lists.py
lookup/__init__.py
lookup/lists.py
lookup/simple.py
test/__init__.py
jasanpy-0.0.4.dist-info/LICENSE.txt
jasanpy-0.0.4.dist-info/METADATA
jasanpy-0.0.4.dist-info/WHEEL
jasanpy-0.0.4.dist-info/entry_points.txt
jasanpy-0.0.4.dist-info/top_level.txt
jasanpy-0.0.4.dist-info/RECORD
