Metadata-Version: 2.1
Name: jasanpy
Version: 0.0.4
Summary: This is a test.
Home-page: https://github.com/jyoo/monpy
Author: James Yoo (Jung Sup Yoo)
Author-email: jungsup.yoo@gmail.com
License: UNKNOWN
Project-URL: Bug Reports, https://github.com/jyoo/monpy/issues
Project-URL: Source, https://github.com/jyoo/monpy/
Keywords: sample,setuptools,development
Platform: UNKNOWN
Classifier: Development Status :: 3 - Alpha
Classifier: Intended Audience :: Developers
Classifier: Topic :: Software Development :: Build Tools
Classifier: License :: OSI Approved :: MIT License
Classifier: Programming Language :: Python :: 3
Classifier: Programming Language :: Python :: 3.6
Classifier: Programming Language :: Python :: 3.7
Classifier: Programming Language :: Python :: 3.8
Classifier: Programming Language :: Python :: 3.9
Classifier: Programming Language :: Python :: 3 :: Only
Requires-Python: >=3.6, <4
Requires-Dist: requests
Provides-Extra: dev
Requires-Dist: check-manifest ; extra == 'dev'
Provides-Extra: test
Requires-Dist: coverage ; extra == 'test'
